sphinxcontrib_markdown-0.1.0-py2.7-nspkg.pth
sphinxcontrib/markdown.py
sphinxcontrib_markdown-0.1.0.dist-info/DESCRIPTION.rst
sphinxcontrib_markdown-0.1.0.dist-info/METADATA
sphinxcontrib_markdown-0.1.0.dist-info/RECORD
sphinxcontrib_markdown-0.1.0.dist-info/WHEEL
sphinxcontrib_markdown-0.1.0.dist-info/metadata.json
sphinxcontrib_markdown-0.1.0.dist-info/namespace_packages.txt
sphinxcontrib_markdown-0.1.0.dist-info/top_level.txt
